[[{"bounding_box": {"y1": 0.0, "x2": 1.0, "x1": 0.0, "y2": 1.0}, "cname": "diner/outdoor", "score": 0.073, "cid": 119}, {"bounding_box": {"y1": 0.0, "x2": 1.0, "x1": 0.0, "y2": 1.0}, "cname": "fastfood_restaurant", "score": 0.064, "cid": 139}, {"bounding_box": {"y1": 0.0, "x2": 1.0, "x1": 0.0, "y2": 1.0}, "cname": "general_store/outdoor", "score": 0.061, "cid": 161}, {"bounding_box": {"y1": 0.0, "x2": 1.0, "x1": 0.0, "y2": 1.0}, "cname": "gas_station", "score": 0.032, "cid": 158}, {"bounding_box": {"y1": 0.0, "x2": 1.0, "x1": 0.0, "y2": 1.0}, "cname": "golf_course", "score": 0.025, "cid": 164}], [{"bounding_box": {"y1": 0.0, "x2": 1.0, "x1": 0.0, "y2": 1.0}, "cname": "motel", "score": 0.079, "cid": 231}, {"bounding_box": {"y1": 0.0, "x2": 1.0, "x1": 0.0, "y2": 1.0}, "cname": "golf_course", "score": 0.063, "cid": 164}, {"bounding_box": {"y1": 0.0, "x2": 1.0, "x1": 0.0, "y2": 1.0}, "cname": "excavation", "score": 0.056, "cid": 136}, {"bounding_box": {"y1": 0.0, "x2": 1.0, "x1": 0.0, "y2": 1.0}, "cname": "industrial_area", "score": 0.047, "cid": 192}, {"bounding_box": {"y1": 0.0, "x2": 1.0, "x1": 0.0, "y2": 1.0}, "cname": "gas_station", "score": 0.034, "cid": 158}], [{"bounding_box": {"y1": 0.0, "x2": 1.0, "x1": 0.0, "y2": 1.0}, "cname": "campsite", "score": 0.371, "cid": 76}, {"bounding_box": {"y1": 0.0, "x2": 1.0, "x1": 0.0, "y2": 1.0}, "cname": "junkyard", "score": 0.088, "cid": 199}, {"bounding_box": {"y1": 0.0, "x2": 1.0, "x1": 0.0, "y2": 1.0}, "cname": "driveway", "score": 0.055, "cid": 127}, {"bounding_box": {"y1": 0.0, "x2": 1.0, "x1": 0.0, "y2": 1.0}, "cname": "greenhouse/outdoor", "score": 0.043, "cid": 166}, {"bounding_box": {"y1": 0.0, "x2": 1.0, "x1": 0.0, "y2": 1.0}, "cname": "parking_lot", "score": 0.036, "cid": 257}], [{"bounding_box": {"y1": 0.0, "x2": 1.0, "x1": 0.0, "y2": 1.0}, "cname": "cockpit", "score": 0.131, "cid": 98}, {"bounding_box": {"y1": 0.0, "x2": 1.0, "x1": 0.0, "y2": 1.0}, "cname": "igloo", "score": 0.125, "cid": 191}, {"bounding_box": {"y1": 0.0, "x2": 1.0, "x1": 0.0, "y2": 1.0}, "cname": "pet_shop", "score": 0.085, "cid": 261}, {"bounding_box": {"y1": 0.0, "x2": 1.0, "x1": 0.0, "y2": 1.0}, "cname": "junkyard", "score": 0.047, "cid": 199}, {"bounding_box": {"y1": 0.0, "x2": 1.0, "x1": 0.0, "y2": 1.0}, "cname": "bus_interior", "score": 0.042, "cid": 70}], [{"bounding_box": {"y1": 0.0, "x2": 1.0, "x1": 0.0, "y2": 1.0}, "cname": "bus_interior", "score": 0.613, "cid": 70}, {"bounding_box": {"y1": 0.0, "x2": 1.0, "x1": 0.0, "y2": 1.0}, "cname": "train_interior", "score": 0.247, "cid": 336}, {"bounding_box": {"y1": 0.0, "x2": 1.0, "x1": 0.0, "y2": 1.0}, "cname": "cockpit", "score": 0.073, "cid": 98}, {"bounding_box": {"y1": 0.0, "x2": 1.0, "x1": 0.0, "y2": 1.0}, "cname": "airplane_cabin", "score": 0.032, "cid": 1}, {"bounding_box": {"y1": 0.0, "x2": 1.0, "x1": 0.0, "y2": 1.0}, "cname": "car_interior", "score": 0.012, "cid": 82}], [{"bounding_box": {"y1": 0.0, "x2": 1.0, "x1": 0.0, "y2": 1.0}, "cname": "bus_interior", "score": 0.642, "cid": 70}, {"bounding_box": {"y1": 0.0, "x2": 1.0, "x1": 0.0, "y2": 1.0}, "cname": "train_interior", "score": 0.259, "cid": 336}, {"bounding_box": {"y1": 0.0, "x2": 1.0, "x1": 0.0, "y2": 1.0}, "cname": "car_interior", "score": 0.046, "cid": 82}, {"bounding_box": {"y1": 0.0, "x2": 1.0, "x1": 0.0, "y2": 1.0}, "cname": "airplane_cabin", "score": 0.019, "cid": 1}, {"bounding_box": {"y1": 0.0, "x2": 1.0, "x1": 0.0, "y2": 1.0}, "cname": "cockpit", "score": 0.016, "cid": 98}], [{"bounding_box": {"y1": 0.0, "x2": 1.0, "x1": 0.0, "y2": 1.0}, "cname": "bus_interior", "score": 0.558, "cid": 70}, {"bounding_box": {"y1": 0.0, "x2": 1.0, "x1": 0.0, "y2": 1.0}, "cname": "train_interior", "score": 0.399, "cid": 336}, {"bounding_box": {"y1": 0.0, "x2": 1.0, "x1": 0.0, "y2": 1.0}, "cname": "airplane_cabin", "score": 0.017, "cid": 1}, {"bounding_box": {"y1": 0.0, "x2": 1.0, "x1": 0.0, "y2": 1.0}, "cname": "cockpit", "score": 0.011, "cid": 98}, {"bounding_box": {"y1": 0.0, "x2": 1.0, "x1": 0.0, "y2": 1.0}, "cname": "car_interior", "score": 0.007, "cid": 82}], [{"bounding_box": {"y1": 0.0, "x2": 1.0, "x1": 0.0, "y2": 1.0}, "cname": "cockpit", "score": 0.302, "cid": 98}, {"bounding_box": {"y1": 0.0, "x2": 1.0, "x1": 0.0, "y2": 1.0}, "cname": "bus_interior", "score": 0.204, "cid": 70}, {"bounding_box": {"y1": 0.0, "x2": 1.0, "x1": 0.0, "y2": 1.0}, "cname": "airplane_cabin", "score": 0.171, "cid": 1}, {"bounding_box": {"y1": 0.0, "x2": 1.0, "x1": 0.0, "y2": 1.0}, "cname": "train_interior", "score": 0.149, "cid": 336}, {"bounding_box": {"y1": 0.0, "x2": 1.0, "x1": 0.0, "y2": 1.0}, "cname": "car_interior", "score": 0.025, "cid": 82}], [{"bounding_box": {"y1": 0.0, "x2": 1.0, "x1": 0.0, "y2": 1.0}, "cname": "amusement_arcade", "score": 0.088, "cid": 6}, {"bounding_box": {"y1": 0.0, "x2": 1.0, "x1": 0.0, "y2": 1.0}, "cname": "delicatessen", "score": 0.062, "cid": 114}, {"bounding_box": {"y1": 0.0, "x2": 1.0, "x1": 0.0, "y2": 1.0}, "cname": "ice_cream_parlor", "score": 0.052, "cid": 185}, {"bounding_box": {"y1": 0.0, "x2": 1.0, "x1": 0.0, "y2": 1.0}, "cname": "amusement_park", "score": 0.047, "cid": 7}, {"bounding_box": {"y1": 0.0, "x2": 1.0, "x1": 0.0, "y2": 1.0}, "cname": "supermarket", "score": 0.043, "cid": 321}], [{"bounding_box": {"y1": 0.0, "x2": 1.0, "x1": 0.0, "y2": 1.0}, "cname": "delicatessen", "score": 0.339, "cid": 114}, {"bounding_box": {"y1": 0.0, "x2": 1.0, "x1": 0.0, "y2": 1.0}, "cname": "pet_shop", "score": 0.121, "cid": 261}, {"bounding_box": {"y1": 0.0, "x2": 1.0, "x1": 0.0, "y2": 1.0}, "cname": "supermarket", "score": 0.078, "cid": 321}, {"bounding_box": {"y1": 0.0, "x2": 1.0, "x1": 0.0, "y2": 1.0}, "cname": "ice_cream_parlor", "score": 0.041, "cid": 185}, {"bounding_box": {"y1": 0.0, "x2": 1.0, "x1": 0.0, "y2": 1.0}, "cname": "sushi_bar", "score": 0.036, "cid": 322}], [{"bounding_box": {"y1": 0.0, "x2": 1.0, "x1": 0.0, "y2": 1.0}, "cname": "delicatessen", "score": 0.069, "cid": 114}, {"bounding_box": {"y1": 0.0, "x2": 1.0, "x1": 0.0, "y2": 1.0}, "cname": "sushi_bar", "score": 0.055, "cid": 322}, {"bounding_box": {"y1": 0.0, "x2": 1.0, "x1": 0.0, "y2": 1.0}, "cname": "fastfood_restaurant", "score": 0.047, "cid": 139}, {"bounding_box": {"y1": 0.0, "x2": 1.0, "x1": 0.0, "y2": 1.0}, "cname": "heliport", "score": 0.043, "cid": 174}, {"bounding_box": {"y1": 0.0, "x2": 1.0, "x1": 0.0, "y2": 1.0}, "cname": "ice_cream_parlor", "score": 0.039, "cid": 185}], [{"bounding_box": {"y1": 0.0, "x2": 1.0, "x1": 0.0, "y2": 1.0}, "cname": "ice_cream_parlor", "score": 0.129, "cid": 185}, {"bounding_box": {"y1": 0.0, "x2": 1.0, "x1": 0.0, "y2": 1.0}, "cname": "delicatessen", "score": 0.092, "cid": 114}, {"bounding_box": {"y1": 0.0, "x2": 1.0, "x1": 0.0, "y2": 1.0}, "cname": "sushi_bar", "score": 0.09, "cid": 322}, {"bounding_box": {"y1": 0.0, "x2": 1.0, "x1": 0.0, "y2": 1.0}, "cname": "coffee_shop", "score": 0.078, "cid": 99}, {"bounding_box": {"y1": 0.0, "x2": 1.0, "x1": 0.0, "y2": 1.0}, "cname": "bar", "score": 0.072, "cid": 39}], [{"bounding_box": {"y1": 0.0, "x2": 1.0, "x1": 0.0, "y2": 1.0}, "cname": "beer_garden", "score": 0.274, "cid": 53}, {"bounding_box": {"y1": 0.0, "x2": 1.0, "x1": 0.0, "y2": 1.0}, "cname": "ice_cream_parlor", "score": 0.242, "cid": 185}, {"bounding_box": {"y1": 0.0, "x2": 1.0, "x1": 0.0, "y2": 1.0}, "cname": "delicatessen", "score": 0.05, "cid": 114}, {"bounding_box": {"y1": 0.0, "x2": 1.0, "x1": 0.0, "y2": 1.0}, "cname": "coffee_shop", "score": 0.048, "cid": 99}, {"bounding_box": {"y1": 0.0, "x2": 1.0, "x1": 0.0, "y2": 1.0}, "cname": "bar", "score": 0.039, "cid": 39}], [{"bounding_box": {"y1": 0.0, "x2": 1.0, "x1": 0.0, "y2": 1.0}, "cname": "bar", "score": 0.211, "cid": 39}, {"bounding_box": {"y1": 0.0, "x2": 1.0, "x1": 0.0, "y2": 1.0}, "cname": "beer_garden", "score": 0.166, "cid": 53}, {"bounding_box": {"y1": 0.0, "x2": 1.0, "x1": 0.0, "y2": 1.0}, "cname": "ice_cream_parlor", "score": 0.079, "cid": 185}, {"bounding_box": {"y1": 0.0, "x2": 1.0, "x1": 0.0, "y2": 1.0}, "cname": "coffee_shop", "score": 0.077, "cid": 99}, {"bounding_box": {"y1": 0.0, "x2": 1.0, "x1": 0.0, "y2": 1.0}, "cname": "beer_hall", "score": 0.074, "cid": 54}], [{"bounding_box": {"y1": 0.0, "x2": 1.0, "x1": 0.0, "y2": 1.0}, "cname": "amusement_arcade", "score": 0.219, "cid": 6}, {"bounding_box": {"y1": 0.0, "x2": 1.0, "x1": 0.0, "y2": 1.0}, "cname": "delicatessen", "score": 0.088, "cid": 114}, {"bounding_box": {"y1": 0.0, "x2": 1.0, "x1": 0.0, "y2": 1.0}, "cname": "art_studio", "score": 0.063, "cid": 21}, {"bounding_box": {"y1": 0.0, "x2": 1.0, "x1": 0.0, "y2": 1.0}, "cname": "ice_cream_parlor", "score": 0.06, "cid": 185}, {"bounding_box": {"y1": 0.0, "x2": 1.0, "x1": 0.0, "y2": 1.0}, "cname": "pet_shop", "score": 0.041, "cid": 261}], [{"bounding_box": {"y1": 0.0, "x2": 1.0, "x1": 0.0, "y2": 1.0}, "cname": "ice_cream_parlor", "score": 0.176, "cid": 185}, {"bounding_box": {"y1": 0.0, "x2": 1.0, "x1": 0.0, "y2": 1.0}, "cname": "train_interior", "score": 0.08, "cid": 336}, {"bounding_box": {"y1": 0.0, "x2": 1.0, "x1": 0.0, "y2": 1.0}, "cname": "fastfood_restaurant", "score": 0.074, "cid": 139}, {"bounding_box": {"y1": 0.0, "x2": 1.0, "x1": 0.0, "y2": 1.0}, "cname": "delicatessen", "score": 0.06, "cid": 114}, {"bounding_box": {"y1": 0.0, "x2": 1.0, "x1": 0.0, "y2": 1.0}, "cname": "amusement_arcade", "score": 0.06, "cid": 6}], [{"bounding_box": {"y1": 0.0, "x2": 1.0, "x1": 0.0, "y2": 1.0}, "cname": "ice_cream_parlor", "score": 0.276, "cid": 185}, {"bounding_box": {"y1": 0.0, "x2": 1.0, "x1": 0.0, "y2": 1.0}, "cname": "amusement_arcade", "score": 0.202, "cid": 6}, {"bounding_box": {"y1": 0.0, "x2": 1.0, "x1": 0.0, "y2": 1.0}, "cname": "toyshop", "score": 0.095, "cid": 335}, {"bounding_box": {"y1": 0.0, "x2": 1.0, "x1": 0.0, "y2": 1.0}, "cname": "delicatessen", "score": 0.052, "cid": 114}, {"bounding_box": {"y1": 0.0, "x2": 1.0, "x1": 0.0, "y2": 1.0}, "cname": "pet_shop", "score": 0.047, "cid": 261}], [{"bounding_box": {"y1": 0.0, "x2": 1.0, "x1": 0.0, "y2": 1.0}, "cname": "sushi_bar", "score": 0.081, "cid": 322}, {"bounding_box": {"y1": 0.0, "x2": 1.0, "x1": 0.0, "y2": 1.0}, "cname": "restaurant_kitchen", "score": 0.054, "cid": 285}, {"bounding_box": {"y1": 0.0, "x2": 1.0, "x1": 0.0, "y2": 1.0}, "cname": "fastfood_restaurant", "score": 0.048, "cid": 139}, {"bounding_box": {"y1": 0.0, "x2": 1.0, "x1": 0.0, "y2": 1.0}, "cname": "airplane_cabin", "score": 0.041, "cid": 1}, {"bounding_box": {"y1": 0.0, "x2": 1.0, "x1": 0.0, "y2": 1.0}, "cname": "amusement_arcade", "score": 0.036, "cid": 6}], [{"bounding_box": {"y1": 0.0, "x2": 1.0, "x1": 0.0, "y2": 1.0}, "cname": "beer_garden", "score": 0.072, "cid": 53}, {"bounding_box": {"y1": 0.0, "x2": 1.0, "x1": 0.0, "y2": 1.0}, "cname": "bus_interior", "score": 0.044, "cid": 70}, {"bounding_box": {"y1": 0.0, "x2": 1.0, "x1": 0.0, "y2": 1.0}, "cname": "amusement_park", "score": 0.041, "cid": 7}, {"bounding_box": {"y1": 0.0, "x2": 1.0, "x1": 0.0, "y2": 1.0}, "cname": "television_studio", "score": 0.038, "cid": 329}, {"bounding_box": {"y1": 0.0, "x2": 1.0, "x1": 0.0, "y2": 1.0}, "cname": "amusement_arcade", "score": 0.033, "cid": 6}], [{"bounding_box": {"y1": 0.0, "x2": 1.0, "x1": 0.0, "y2": 1.0}, "cname": "ice_cream_parlor", "score": 0.197, "cid": 185}, {"bounding_box": {"y1": 0.0, "x2": 1.0, "x1": 0.0, "y2": 1.0}, "cname": "bakery/shop", "score": 0.158, "cid": 31}, {"bounding_box": {"y1": 0.0, "x2": 1.0, "x1": 0.0, "y2": 1.0}, "cname": "shopfront", "score": 0.081, "cid": 301}, {"bounding_box": {"y1": 0.0, "x2": 1.0, "x1": 0.0, "y2": 1.0}, "cname": "delicatessen", "score": 0.043, "cid": 114}, {"bounding_box": {"y1": 0.0, "x2": 1.0, "x1": 0.0, "y2": 1.0}, "cname": "clothing_store", "score": 0.029, "cid": 96}], [{"bounding_box": {"y1": 0.0, "x2": 1.0, "x1": 0.0, "y2": 1.0}, "cname": "bakery/shop", "score": 0.829, "cid": 31}, {"bounding_box": {"y1": 0.0, "x2": 1.0, "x1": 0.0, "y2": 1.0}, "cname": "delicatessen", "score": 0.062, "cid": 114}, {"bounding_box": {"y1": 0.0, "x2": 1.0, "x1": 0.0, "y2": 1.0}, "cname": "coffee_shop", "score": 0.033, "cid": 99}, {"bounding_box": {"y1": 0.0, "x2": 1.0, "x1": 0.0, "y2": 1.0}, "cname": "candy_store", "score": 0.011, "cid": 80}, {"bounding_box": {"y1": 0.0, "x2": 1.0, "x1": 0.0, "y2": 1.0}, "cname": "fastfood_restaurant", "score": 0.01, "cid": 139}], [{"bounding_box": {"y1": 0.0, "x2": 1.0, "x1": 0.0, "y2": 1.0}, "cname": "bakery/shop", "score": 0.666, "cid": 31}, {"bounding_box": {"y1": 0.0, "x2": 1.0, "x1": 0.0, "y2": 1.0}, "cname": "delicatessen", "score": 0.14, "cid": 114}, {"bounding_box": {"y1": 0.0, "x2": 1.0, "x1": 0.0, "y2": 1.0}, "cname": "coffee_shop", "score": 0.057, "cid": 99}, {"bounding_box": {"y1": 0.0, "x2": 1.0, "x1": 0.0, "y2": 1.0}, "cname": "candy_store", "score": 0.031, "cid": 80}, {"bounding_box": {"y1": 0.0, "x2": 1.0, "x1": 0.0, "y2": 1.0}, "cname": "fastfood_restaurant", "score": 0.015, "cid": 139}], [{"bounding_box": {"y1": 0.0, "x2": 1.0, "x1": 0.0, "y2": 1.0}, "cname": "bakery/shop", "score": 0.64, "cid": 31}, {"bounding_box": {"y1": 0.0, "x2": 1.0, "x1": 0.0, "y2": 1.0}, "cname": "delicatessen", "score": 0.156, "cid": 114}, {"bounding_box": {"y1": 0.0, "x2": 1.0, "x1": 0.0, "y2": 1.0}, "cname": "coffee_shop", "score": 0.076, "cid": 99}, {"bounding_box": {"y1": 0.0, "x2": 1.0, "x1": 0.0, "y2": 1.0}, "cname": "candy_store", "score": 0.027, "cid": 80}, {"bounding_box": {"y1": 0.0, "x2": 1.0, "x1": 0.0, "y2": 1.0}, "cname": "fastfood_restaurant", "score": 0.023, "cid": 139}], [{"bounding_box": {"y1": 0.0, "x2": 1.0, "x1": 0.0, "y2": 1.0}, "cname": "bakery/shop", "score": 0.526, "cid": 31}, {"bounding_box": {"y1": 0.0, "x2": 1.0, "x1": 0.0, "y2": 1.0}, "cname": "delicatessen", "score": 0.174, "cid": 114}, {"bounding_box": {"y1": 0.0, "x2": 1.0, "x1": 0.0, "y2": 1.0}, "cname": "coffee_shop", "score": 0.129, "cid": 99}, {"bounding_box": {"y1": 0.0, "x2": 1.0, "x1": 0.0, "y2": 1.0}, "cname": "candy_store", "score": 0.031, "cid": 80}, {"bounding_box": {"y1": 0.0, "x2": 1.0, "x1": 0.0, "y2": 1.0}, "cname": "fastfood_restaurant", "score": 0.028, "cid": 139}], [{"bounding_box": {"y1": 0.0, "x2": 1.0, "x1": 0.0, "y2": 1.0}, "cname": "bakery/shop", "score": 0.627, "cid": 31}, {"bounding_box": {"y1": 0.0, "x2": 1.0, "x1": 0.0, "y2": 1.0}, "cname": "delicatessen", "score": 0.169, "cid": 114}, {"bounding_box": {"y1": 0.0, "x2": 1.0, "x1": 0.0, "y2": 1.0}, "cname": "coffee_shop", "score": 0.051, "cid": 99}, {"bounding_box": {"y1": 0.0, "x2": 1.0, "x1": 0.0, "y2": 1.0}, "cname": "candy_store", "score": 0.042, "cid": 80}, {"bounding_box": {"y1": 0.0, "x2": 1.0, "x1": 0.0, "y2": 1.0}, "cname": "fastfood_restaurant", "score": 0.023, "cid": 139}], [{"bounding_box": {"y1": 0.0, "x2": 1.0, "x1": 0.0, "y2": 1.0}, "cname": "ticket_booth", "score": 0.137, "cid": 332}, {"bounding_box": {"y1": 0.0, "x2": 1.0, "x1": 0.0, "y2": 1.0}, "cname": "ice_cream_parlor", "score": 0.117, "cid": 185}, {"bounding_box": {"y1": 0.0, "x2": 1.0, "x1": 0.0, "y2": 1.0}, "cname": "amusement_park", "score": 0.075, "cid": 7}, {"bounding_box": {"y1": 0.0, "x2": 1.0, "x1": 0.0, "y2": 1.0}, "cname": "fastfood_restaurant", "score": 0.07, "cid": 139}, {"bounding_box": {"y1": 0.0, "x2": 1.0, "x1": 0.0, "y2": 1.0}, "cname": "pharmacy", "score": 0.054, "cid": 262}], [{"bounding_box": {"y1": 0.0, "x2": 1.0, "x1": 0.0, "y2": 1.0}, "cname": "ice_cream_parlor", "score": 0.146, "cid": 185}, {"bounding_box": {"y1": 0.0, "x2": 1.0, "x1": 0.0, "y2": 1.0}, "cname": "ticket_booth", "score": 0.097, "cid": 332}, {"bounding_box": {"y1": 0.0, "x2": 1.0, "x1": 0.0, "y2": 1.0}, "cname": "fastfood_restaurant", "score": 0.085, "cid": 139}, {"bounding_box": {"y1": 0.0, "x2": 1.0, "x1": 0.0, "y2": 1.0}, "cname": "pharmacy", "score": 0.066, "cid": 262}, {"bounding_box": {"y1": 0.0, "x2": 1.0, "x1": 0.0, "y2": 1.0}, "cname": "pet_shop", "score": 0.062, "cid": 261}], [{"bounding_box": {"y1": 0.0, "x2": 1.0, "x1": 0.0, "y2": 1.0}, "cname": "ticket_booth", "score": 0.136, "cid": 332}, {"bounding_box": {"y1": 0.0, "x2": 1.0, "x1": 0.0, "y2": 1.0}, "cname": "fastfood_restaurant", "score": 0.129, "cid": 139}, {"bounding_box": {"y1": 0.0, "x2": 1.0, "x1": 0.0, "y2": 1.0}, "cname": "ice_cream_parlor", "score": 0.095, "cid": 185}, {"bounding_box": {"y1": 0.0, "x2": 1.0, "x1": 0.0, "y2": 1.0}, "cname": "pharmacy", "score": 0.067, "cid": 262}, {"bounding_box": {"y1": 0.0, "x2": 1.0, "x1": 0.0, "y2": 1.0}, "cname": "delicatessen", "score": 0.063, "cid": 114}], [{"bounding_box": {"y1": 0.0, "x2": 1.0, "x1": 0.0, "y2": 1.0}, "cname": "ice_cream_parlor", "score": 0.224, "cid": 185}, {"bounding_box": {"y1": 0.0, "x2": 1.0, "x1": 0.0, "y2": 1.0}, "cname": "fastfood_restaurant", "score": 0.111, "cid": 139}, {"bounding_box": {"y1": 0.0, "x2": 1.0, "x1": 0.0, "y2": 1.0}, "cname": "delicatessen", "score": 0.085, "cid": 114}, {"bounding_box": {"y1": 0.0, "x2": 1.0, "x1": 0.0, "y2": 1.0}, "cname": "pharmacy", "score": 0.064, "cid": 262}, {"bounding_box": {"y1": 0.0, "x2": 1.0, "x1": 0.0, "y2": 1.0}, "cname": "booth/indoor", "score": 0.046, "cid": 61}], [{"bounding_box": {"y1": 0.0, "x2": 1.0, "x1": 0.0, "y2": 1.0}, "cname": "ticket_booth", "score": 0.129, "cid": 332}, {"bounding_box": {"y1": 0.0, "x2": 1.0, "x1": 0.0, "y2": 1.0}, "cname": "pharmacy", "score": 0.106, "cid": 262}, {"bounding_box": {"y1": 0.0, "x2": 1.0, "x1": 0.0, "y2": 1.0}, "cname": "ice_cream_parlor", "score": 0.085, "cid": 185}, {"bounding_box": {"y1": 0.0, "x2": 1.0, "x1": 0.0, "y2": 1.0}, "cname": "pet_shop", "score": 0.076, "cid": 261}, {"bounding_box": {"y1": 0.0, "x2": 1.0, "x1": 0.0, "y2": 1.0}, "cname": "drugstore", "score": 0.063, "cid": 128}], [{"bounding_box": {"y1": 0.0, "x2": 1.0, "x1": 0.0, "y2": 1.0}, "cname": "stage/indoor", "score": 0.037, "cid": 315}, {"bounding_box": {"y1": 0.0, "x2": 1.0, "x1": 0.0, "y2": 1.0}, "cname": "sky", "score": 0.037, "cid": 306}, {"bounding_box": {"y1": 0.0, "x2": 1.0, "x1": 0.0, "y2": 1.0}, "cname": "catacomb", "score": 0.028, "cid": 85}, {"bounding_box": {"y1": 0.0, "x2": 1.0, "x1": 0.0, "y2": 1.0}, "cname": "movie_theater/indoor", "score": 0.026, "cid": 235}, {"bounding_box": {"y1": 0.0, "x2": 1.0, "x1": 0.0, "y2": 1.0}, "cname": "windmill", "score": 0.025, "cid": 361}]]