[[{"bounding_box": {"y1": 0.3622, "x2": 0.2463, "x1": 0.0522, "y2": 0.9753}, "cname": "potted plant", "score": 0.6192, "cid": 63}, {"bounding_box": {"y1": 0.1101, "x2": 0.7084, "x1": 0.3256, "y2": 0.4965}, "cname": "tv", "score": 0.38, "cid": 71}, {"bounding_box": {"y1": 0.5994, "x2": 0.2495, "x1": 0.0929, "y2": 0.9883}, "cname": "potted plant", "score": 0.2686, "cid": 63}, {"bounding_box": {"y1": 0.3826, "x2": 0.1996, "x1": 0.0784, "y2": 0.6859}, "cname": "potted plant", "score": 0.2311, "cid": 63}, {"bounding_box": {"y1": 0.6917, "x2": 0.701, "x1": 0.3186, "y2": 0.9948}, "cname": "tv", "score": 0.1662, "cid": 71}, {"bounding_box": {"y1": 0.1161, "x2": 0.7269, "x1": 0.2905, "y2": 0.8197}, "cname": "tv", "score": 0.1108, "cid": 71}, {"bounding_box": {"y1": 0.6546, "x2": 0.9886, "x1": 0.8744, "y2": 0.8726}, "cname": "book", "score": 0.1042, "cid": 83}], [{"bounding_box": {"y1": 0.5681, "x2": 0.3015, "x1": 0.0026, "y2": 0.9533}, "cname": "chair", "score": 0.2559, "cid": 61}, {"bounding_box": {"y1": 0.577, "x2": 0.8401, "x1": 0.0402, "y2": 0.9962}, "cname": "person", "score": 0.2549, "cid": 0}, {"bounding_box": {"y1": 0.309, "x2": 0.5033, "x1": 0.3144, "y2": 0.5777}, "cname": "chair", "score": 0.2512, "cid": 61}, {"bounding_box": {"y1": 0.1474, "x2": 0.9629, "x1": 0.0319, "y2": 0.9996}, "cname": "person", "score": 0.1896, "cid": 0}, {"bounding_box": {"y1": 0.7416, "x2": 0.8174, "x1": 0.3171, "y2": 0.9979}, "cname": "chair", "score": 0.1866, "cid": 61}, {"bounding_box": {"y1": 0.3371, "x2": 0.6049, "x1": 0.3176, "y2": 0.717}, "cname": "chair", "score": 0.1682, "cid": 61}, {"bounding_box": {"y1": 0.4282, "x2": 0.5385, "x1": 0.0502, "y2": 0.9846}, "cname": "person", "score": 0.149, "cid": 0}, {"bounding_box": {"y1": 0.0437, "x2": 0.425, "x1": 0.0, "y2": 0.9844}, "cname": "person", "score": 0.1248, "cid": 0}, {"bounding_box": {"y1": 0.0, "x2": 0.327, "x1": 0.2258, "y2": 0.287}, "cname": "book", "score": 0.1025, "cid": 83}], [{"bounding_box": {"y1": 0.2159, "x2": 0.8307, "x1": 0.1093, "y2": 0.9559}, "cname": "person", "score": 0.7808, "cid": 0}, {"bounding_box": {"y1": 0.0928, "x2": 0.8869, "x1": 0.6922, "y2": 0.5238}, "cname": "chair", "score": 0.7588, "cid": 61}, {"bounding_box": {"y1": 0.493, "x2": 0.2198, "x1": 0.0378, "y2": 0.7132}, "cname": "chair", "score": 0.2638, "cid": 61}, {"bounding_box": {"y1": 0.5247, "x2": 0.9631, "x1": 0.0253, "y2": 0.9995}, "cname": "couch", "score": 0.2514, "cid": 62}, {"bounding_box": {"y1": 0.3437, "x2": 0.6838, "x1": 0.3969, "y2": 0.7018}, "cname": "chair", "score": 0.2006, "cid": 61}, {"bounding_box": {"y1": 0.4893, "x2": 0.5772, "x1": 0.1078, "y2": 0.7595}, "cname": "chair", "score": 0.1746, "cid": 61}, {"bounding_box": {"y1": 0.3158, "x2": 0.7008, "x1": 0.0216, "y2": 0.9599}, "cname": "couch", "score": 0.1619, "cid": 62}, {"bounding_box": {"y1": 0.1827, "x2": 1.0, "x1": 0.713, "y2": 0.9771}, "cname": "person", "score": 0.1411, "cid": 0}, {"bounding_box": {"y1": 0.2121, "x2": 0.9912, "x1": 0.3949, "y2": 0.9477}, "cname": "person", "score": 0.1353, "cid": 0}, {"bounding_box": {"y1": 0.1248, "x2": 0.557, "x1": 0.0, "y2": 0.9246}, "cname": "person", "score": 0.1217, "cid": 0}], [{"bounding_box": {"y1": 0.1833, "x2": 0.9312, "x1": 0.0338, "y2": 0.9994}, "cname": "person", "score": 0.6026, "cid": 0}, {"bounding_box": {"y1": 0.2333, "x2": 0.6555, "x1": 0.1996, "y2": 0.7491}, "cname": "chair", "score": 0.3239, "cid": 61}, {"bounding_box": {"y1": 0.101, "x2": 0.8424, "x1": 0.6803, "y2": 0.6463}, "cname": "chair", "score": 0.2356, "cid": 61}, {"bounding_box": {"y1": 0.0707, "x2": 0.851, "x1": 0.6861, "y2": 0.3361}, "cname": "chair", "score": 0.2077, "cid": 61}, {"bounding_box": {"y1": 0.2867, "x2": 0.643, "x1": 0.3716, "y2": 0.6838}, "cname": "chair", "score": 0.1925, "cid": 61}, {"bounding_box": {"y1": 0.2281, "x2": 0.7596, "x1": 0.6471, "y2": 0.5369}, "cname": "cup", "score": 0.1845, "cid": 46}, {"bounding_box": {"y1": 0.1829, "x2": 0.8345, "x1": 0.6842, "y2": 0.5316}, "cname": "cup", "score": 0.1441, "cid": 46}, {"bounding_box": {"y1": 0.1125, "x2": 0.5779, "x1": 0.0044, "y2": 0.9101}, "cname": "person", "score": 0.1301, "cid": 0}, {"bounding_box": {"y1": 0.3237, "x2": 0.9972, "x1": 0.6837, "y2": 0.9929}, "cname": "person", "score": 0.1239, "cid": 0}, {"bounding_box": {"y1": 0.4174, "x2": 0.9919, "x1": 0.3826, "y2": 0.9928}, "cname": "person", "score": 0.1037, "cid": 0}], [{"bounding_box": {"y1": 0.1727, "x2": 0.9692, "x1": 0.0313, "y2": 1.0}, "cname": "person", "score": 0.5553, "cid": 0}, {"bounding_box": {"y1": 0.0974, "x2": 0.8475, "x1": 0.6543, "y2": 0.5411}, "cname": "chair", "score": 0.526, "cid": 61}, {"bounding_box": {"y1": 0.335, "x2": 0.6532, "x1": 0.3514, "y2": 0.7215}, "cname": "chair", "score": 0.3179, "cid": 61}, {"bounding_box": {"y1": 0.2107, "x2": 0.8634, "x1": 0.6378, "y2": 0.723}, "cname": "chair", "score": 0.2492, "cid": 61}, {"bounding_box": {"y1": 0.3701, "x2": 0.7683, "x1": 0.2048, "y2": 0.9431}, "cname": "chair", "score": 0.2364, "cid": 61}, {"bounding_box": {"y1": 0.6153, "x2": 0.4682, "x1": 0.1558, "y2": 0.7512}, "cname": "handbag", "score": 0.1962, "cid": 30}, {"bounding_box": {"y1": 0.2603, "x2": 0.668, "x1": 0.0272, "y2": 0.8037}, "cname": "person", "score": 0.1865, "cid": 0}, {"bounding_box": {"y1": 0.5165, "x2": 0.9909, "x1": 0.6628, "y2": 0.971}, "cname": "handbag", "score": 0.1454, "cid": 30}, {"bounding_box": {"y1": 0.4962, "x2": 0.9762, "x1": 0.0164, "y2": 0.9865}, "cname": "couch", "score": 0.1195, "cid": 62}, {"bounding_box": {"y1": 0.5462, "x2": 0.447, "x1": 0.0054, "y2": 0.9733}, "cname": "couch", "score": 0.1108, "cid": 62}, {"bounding_box": {"y1": 0.0775, "x2": 0.8367, "x1": 0.6542, "y2": 0.3878}, "cname": "cup", "score": 0.1089, "cid": 46}, {"bounding_box": {"y1": 0.1709, "x2": 0.8017, "x1": 0.6519, "y2": 0.4602}, "cname": "cup", "score": 0.1022, "cid": 46}], [{"bounding_box": {"y1": 0.0149, "x2": 0.9245, "x1": 0.0879, "y2": 0.9962}, "cname": "person", "score": 0.6134, "cid": 0}, {"bounding_box": {"y1": 0.5939, "x2": 1.0, "x1": 0.8669, "y2": 1.0}, "cname": "chair", "score": 0.1405, "cid": 61}, {"bounding_box": {"y1": 0.6495, "x2": 0.9315, "x1": 0.6672, "y2": 0.9897}, "cname": "chair", "score": 0.1341, "cid": 61}, {"bounding_box": {"y1": 0.0312, "x2": 0.2383, "x1": 0.0045, "y2": 0.9689}, "cname": "person", "score": 0.1134, "cid": 0}, {"bounding_box": {"y1": 0.6694, "x2": 0.9107, "x1": 0.1329, "y2": 0.9954}, "cname": "chair", "score": 0.1092, "cid": 61}], [{"bounding_box": {"y1": 0.0166, "x2": 0.9387, "x1": 0.0422, "y2": 0.998}, "cname": "person", "score": 0.6402, "cid": 0}, {"bounding_box": {"y1": 0.65, "x2": 0.8814, "x1": 0.6391, "y2": 0.8478}, "cname": "chair", "score": 0.1086, "cid": 61}, {"bounding_box": {"y1": 0.3664, "x2": 1.0, "x1": 0.8747, "y2": 0.9916}, "cname": "person", "score": 0.1062, "cid": 0}, {"bounding_box": {"y1": 0.596, "x2": 1.0, "x1": 0.8758, "y2": 1.0}, "cname": "chair", "score": 0.1057, "cid": 61}, {"bounding_box": {"y1": 0.1075, "x2": 0.2209, "x1": 0.0047, "y2": 0.9993}, "cname": "person", "score": 0.1037, "cid": 0}], [{"bounding_box": {"y1": 0.0354, "x2": 0.9818, "x1": 0.0097, "y2": 0.988}, "cname": "person", "score": 0.6061, "cid": 0}, {"bounding_box": {"y1": 0.6055, "x2": 0.9002, "x1": 0.037, "y2": 0.9977}, "cname": "chair", "score": 0.2195, "cid": 61}, {"bounding_box": {"y1": 0.5834, "x2": 0.9245, "x1": 0.0375, "y2": 0.978}, "cname": "couch", "score": 0.1356, "cid": 62}, {"bounding_box": {"y1": 0.359, "x2": 1.0, "x1": 0.8701, "y2": 0.9979}, "cname": "person", "score": 0.1344, "cid": 0}, {"bounding_box": {"y1": 0.6893, "x2": 0.8999, "x1": 0.7285, "y2": 0.9728}, "cname": "chair", "score": 0.1246, "cid": 61}, {"bounding_box": {"y1": 0.8512, "x2": 1.0, "x1": 0.6867, "y2": 0.9911}, "cname": "chair", "score": 0.1142, "cid": 61}, {"bounding_box": {"y1": 0.1007, "x2": 0.3661, "x1": 0.231, "y2": 0.3307}, "cname": "book", "score": 0.1019, "cid": 83}], [{"bounding_box": {"y1": 0.3284, "x2": 0.5853, "x1": 0.4281, "y2": 0.8605}, "cname": "person", "score": 0.8224, "cid": 0}, {"bounding_box": {"y1": 0.3489, "x2": 0.5656, "x1": 0.4367, "y2": 0.8003}, "cname": "handbag", "score": 0.1081, "cid": 30}, {"bounding_box": {"y1": 0.5466, "x2": 0.5952, "x1": 0.4763, "y2": 0.8466}, "cname": "person", "score": 0.1004, "cid": 0}, {"bounding_box": {"y1": 0.3489, "x2": 0.5656, "x1": 0.4367, "y2": 0.8003}, "cname": "backpack", "score": 0.1003, "cid": 26}], [{"bounding_box": {"y1": 0.214, "x2": 0.5979, "x1": 0.4016, "y2": 0.8777}, "cname": "person", "score": 0.8092, "cid": 0}, {"bounding_box": {"y1": 0.657, "x2": 0.9534, "x1": 0.0543, "y2": 0.9777}, "cname": "bed", "score": 0.2279, "cid": 64}, {"bounding_box": {"y1": 0.7331, "x2": 0.7281, "x1": 0.1375, "y2": 0.9408}, "cname": "bed", "score": 0.1332, "cid": 64}, {"bounding_box": {"y1": 0.058, "x2": 0.5768, "x1": 0.0737, "y2": 0.6713}, "cname": "tv", "score": 0.1303, "cid": 71}, {"bounding_box": {"y1": 0.6354, "x2": 0.5827, "x1": 0.4335, "y2": 0.8599}, "cname": "chair", "score": 0.1292, "cid": 61}, {"bounding_box": {"y1": 0.7078, "x2": 0.5583, "x1": 0.4468, "y2": 0.8439}, "cname": "chair", "score": 0.1145, "cid": 61}], [{"bounding_box": {"y1": 0.7242, "x2": 0.9055, "x1": 0.7472, "y2": 0.9984}, "cname": "chair", "score": 0.7967, "cid": 61}, {"bounding_box": {"y1": 0.3626, "x2": 0.6018, "x1": 0.3752, "y2": 0.9772}, "cname": "person", "score": 0.7738, "cid": 0}, {"bounding_box": {"y1": 0.2204, "x2": 0.2583, "x1": 0.0042, "y2": 0.9968}, "cname": "person", "score": 0.6331, "cid": 0}, {"bounding_box": {"y1": 0.2285, "x2": 0.1466, "x1": 0.0134, "y2": 0.442}, "cname": "person", "score": 0.131, "cid": 0}, {"bounding_box": {"y1": 0.787, "x2": 0.4589, "x1": 0.2479, "y2": 0.9955}, "cname": "chair", "score": 0.1156, "cid": 61}, {"bounding_box": {"y1": 0.7276, "x2": 0.253, "x1": 0.107, "y2": 0.9759}, "cname": "chair", "score": 0.1123, "cid": 61}, {"bounding_box": {"y1": 0.7705, "x2": 0.2947, "x1": 0.15, "y2": 1.0}, "cname": "chair", "score": 0.1017, "cid": 61}], [{"bounding_box": {"y1": 0.3294, "x2": 0.6101, "x1": 0.3585, "y2": 0.9996}, "cname": "person", "score": 0.7026, "cid": 0}, {"bounding_box": {"y1": 0.2393, "x2": 0.2838, "x1": 0.0862, "y2": 0.9919}, "cname": "person", "score": 0.647, "cid": 0}, {"bounding_box": {"y1": 0.7392, "x2": 0.9366, "x1": 0.765, "y2": 0.9943}, "cname": "chair", "score": 0.385, "cid": 61}, {"bounding_box": {"y1": 0.6863, "x2": 0.2584, "x1": 0.0988, "y2": 1.0}, "cname": "chair", "score": 0.1163, "cid": 61}], [{"bounding_box": {"y1": 0.2737, "x2": 0.6203, "x1": 0.3537, "y2": 1.0}, "cname": "person", "score": 0.772, "cid": 0}, {"bounding_box": {"y1": 0.2116, "x2": 0.2519, "x1": 0.0708, "y2": 0.9608}, "cname": "person", "score": 0.651, "cid": 0}, {"bounding_box": {"y1": 0.7533, "x2": 0.9754, "x1": 0.7955, "y2": 0.9935}, "cname": "chair", "score": 0.2581, "cid": 61}, {"bounding_box": {"y1": 0.2132, "x2": 0.3189, "x1": 0.1824, "y2": 0.8465}, "cname": "person", "score": 0.1845, "cid": 0}, {"bounding_box": {"y1": 0.7451, "x2": 0.1295, "x1": 0.0228, "y2": 0.9888}, "cname": "chair", "score": 0.1197, "cid": 61}, {"bounding_box": {"y1": 0.6661, "x2": 0.2343, "x1": 0.0965, "y2": 0.9888}, "cname": "chair", "score": 0.1092, "cid": 61}], [{"bounding_box": {"y1": 0.2113, "x2": 0.5302, "x1": 0.3195, "y2": 0.9552}, "cname": "person", "score": 0.7238, "cid": 0}, {"bounding_box": {"y1": 0.1949, "x2": 0.2391, "x1": 0.0669, "y2": 0.957}, "cname": "person", "score": 0.7026, "cid": 0}, {"bounding_box": {"y1": 0.7617, "x2": 0.9814, "x1": 0.801, "y2": 0.992}, "cname": "chair", "score": 0.2552, "cid": 61}, {"bounding_box": {"y1": 0.2122, "x2": 0.316, "x1": 0.1914, "y2": 0.8579}, "cname": "person", "score": 0.1618, "cid": 0}, {"bounding_box": {"y1": 0.813, "x2": 0.8331, "x1": 0.4823, "y2": 1.0}, "cname": "chair", "score": 0.1362, "cid": 61}, {"bounding_box": {"y1": 0.7275, "x2": 0.5296, "x1": 0.3501, "y2": 0.97}, "cname": "chair", "score": 0.1075, "cid": 61}], [{"bounding_box": {"y1": 0.2111, "x2": 0.2397, "x1": 0.0727, "y2": 0.9561}, "cname": "person", "score": 0.6796, "cid": 0}, {"bounding_box": {"y1": 0.1571, "x2": 0.5673, "x1": 0.2133, "y2": 0.9769}, "cname": "person", "score": 0.254, "cid": 0}, {"bounding_box": {"y1": 0.7607, "x2": 0.9842, "x1": 0.8002, "y2": 0.9884}, "cname": "chair", "score": 0.2037, "cid": 61}, {"bounding_box": {"y1": 0.1707, "x2": 0.2938, "x1": 0.1914, "y2": 0.6085}, "cname": "person", "score": 0.1651, "cid": 0}, {"bounding_box": {"y1": 0.2185, "x2": 0.3093, "x1": 0.168, "y2": 0.9054}, "cname": "person", "score": 0.1548, "cid": 0}, {"bounding_box": {"y1": 0.7464, "x2": 0.1281, "x1": 0.0084, "y2": 0.9865}, "cname": "chair", "score": 0.1066, "cid": 61}], [{"bounding_box": {"y1": 0.2809, "x2": 0.4822, "x1": 0.2905, "y2": 0.7988}, "cname": "person", "score": 0.7504, "cid": 0}, {"bounding_box": {"y1": 0.1395, "x2": 0.8436, "x1": 0.267, "y2": 0.9933}, "cname": "person", "score": 0.4078, "cid": 0}, {"bounding_box": {"y1": 0.2836, "x2": 0.4964, "x1": 0.3269, "y2": 0.6058}, "cname": "person", "score": 0.1878, "cid": 0}, {"bounding_box": {"y1": 0.3241, "x2": 0.481, "x1": 0.2009, "y2": 0.9951}, "cname": "person", "score": 0.1092, "cid": 0}, {"bounding_box": {"y1": 0.7286, "x2": 0.1071, "x1": 0.0004, "y2": 0.9826}, "cname": "chair", "score": 0.103, "cid": 61}], [{"bounding_box": {"y1": 0.3108, "x2": 0.4053, "x1": 0.2277, "y2": 0.7708}, "cname": "person", "score": 0.9372, "cid": 0}, {"bounding_box": {"y1": 0.6821, "x2": 0.7096, "x1": 0.5508, "y2": 0.9984}, "cname": "tie", "score": 0.481, "cid": 31}, {"bounding_box": {"y1": 0.073, "x2": 0.8584, "x1": 0.1729, "y2": 1.0}, "cname": "person", "score": 0.4595, "cid": 0}, {"bounding_box": {"y1": 0.274, "x2": 0.4097, "x1": 0.2778, "y2": 0.654}, "cname": "person", "score": 0.2295, "cid": 0}, {"bounding_box": {"y1": 0.2574, "x2": 0.4121, "x1": 0.1585, "y2": 0.9304}, "cname": "person", "score": 0.14, "cid": 0}], [{"bounding_box": {"y1": 0.7197, "x2": 0.6364, "x1": 0.4964, "y2": 1.0}, "cname": "tie", "score": 0.7981, "cid": 31}, {"bounding_box": {"y1": 0.3113, "x2": 0.3959, "x1": 0.1908, "y2": 0.7893}, "cname": "person", "score": 0.6279, "cid": 0}, {"bounding_box": {"y1": 0.0, "x2": 0.9235, "x1": 0.1161, "y2": 1.0}, "cname": "person", "score": 0.4022, "cid": 0}, {"bounding_box": {"y1": 0.3144, "x2": 0.3243, "x1": 0.1716, "y2": 0.6448}, "cname": "person", "score": 0.1408, "cid": 0}], [{"bounding_box": {"y1": 0.7183, "x2": 0.6355, "x1": 0.4939, "y2": 1.0}, "cname": "tie", "score": 0.9082, "cid": 31}, {"bounding_box": {"y1": 0.3074, "x2": 0.3901, "x1": 0.1882, "y2": 0.7966}, "cname": "person", "score": 0.7499, "cid": 0}, {"bounding_box": {"y1": 0.0, "x2": 0.9231, "x1": 0.1047, "y2": 1.0}, "cname": "person", "score": 0.4179, "cid": 0}, {"bounding_box": {"y1": 0.3149, "x2": 0.3147, "x1": 0.1717, "y2": 0.6515}, "cname": "person", "score": 0.1424, "cid": 0}], [{"bounding_box": {"y1": 0.1042, "x2": 0.6836, "x1": 0.1817, "y2": 1.0}, "cname": "person", "score": 0.621, "cid": 0}, {"bounding_box": {"y1": 0.0655, "x2": 0.2735, "x1": 0.0097, "y2": 0.3942}, "cname": "tv", "score": 0.1037, "cid": 71}], [{"bounding_box": {"y1": 0.0477, "x2": 0.6655, "x1": 0.1657, "y2": 0.9936}, "cname": "person", "score": 0.6412, "cid": 0}], [{"bounding_box": {"y1": 0.0464, "x2": 0.6542, "x1": 0.156, "y2": 0.9924}, "cname": "person", "score": 0.65, "cid": 0}], [{"bounding_box": {"y1": 0.0419, "x2": 0.6554, "x1": 0.1398, "y2": 0.9968}, "cname": "person", "score": 0.6229, "cid": 0}], [{"bounding_box": {"y1": 0.1158, "x2": 0.732, "x1": 0.4195, "y2": 1.0}, "cname": "person", "score": 0.446, "cid": 0}, {"bounding_box": {"y1": 0.3529, "x2": 0.3122, "x1": 0.1302, "y2": 0.9752}, "cname": "person", "score": 0.2364, "cid": 0}, {"bounding_box": {"y1": 0.1054, "x2": 0.2798, "x1": 0.0003, "y2": 0.9499}, "cname": "potted plant", "score": 0.1127, "cid": 63}, {"bounding_box": {"y1": 0.1151, "x2": 0.8897, "x1": 0.2293, "y2": 1.0}, "cname": "person", "score": 0.1117, "cid": 0}, {"bounding_box": {"y1": 0.3575, "x2": 0.3089, "x1": 0.1306, "y2": 0.9647}, "cname": "vase", "score": 0.1045, "cid": 85}], [{"bounding_box": {"y1": 0.1363, "x2": 0.6055, "x1": 0.3667, "y2": 0.9962}, "cname": "person", "score": 0.757, "cid": 0}, {"bounding_box": {"y1": 0.2281, "x2": 0.4248, "x1": 0.2115, "y2": 0.9908}, "cname": "person", "score": 0.7542, "cid": 0}, {"bounding_box": {"y1": 0.0663, "x2": 0.8262, "x1": 0.526, "y2": 1.0}, "cname": "person", "score": 0.663, "cid": 0}, {"bounding_box": {"y1": 0.1235, "x2": 0.5929, "x1": 0.4221, "y2": 0.4192}, "cname": "person", "score": 0.1735, "cid": 0}], [{"bounding_box": {"y1": 0.082, "x2": 0.9559, "x1": 0.2286, "y2": 1.0}, "cname": "person", "score": 0.8706, "cid": 0}, {"bounding_box": {"y1": 0.0162, "x2": 0.4855, "x1": 0.0032, "y2": 0.9978}, "cname": "person", "score": 0.4296, "cid": 0}, {"bounding_box": {"y1": 0.7769, "x2": 0.2637, "x1": 0.1048, "y2": 0.9944}, "cname": "person", "score": 0.1013, "cid": 0}], [{"bounding_box": {"y1": 0.0173, "x2": 0.9234, "x1": 0.2796, "y2": 1.0}, "cname": "person", "score": 0.88, "cid": 0}, {"bounding_box": {"y1": 0.0101, "x2": 0.3943, "x1": 0.0009, "y2": 0.9945}, "cname": "person", "score": 0.3556, "cid": 0}, {"bounding_box": {"y1": 0.1861, "x2": 0.2105, "x1": 0.0532, "y2": 0.4464}, "cname": "cell phone", "score": 0.1254, "cid": 76}], [{"bounding_box": {"y1": 0.0617, "x2": 0.9426, "x1": 0.3689, "y2": 0.9941}, "cname": "person", "score": 0.8043, "cid": 0}, {"bounding_box": {"y1": 0.1336, "x2": 0.629, "x1": 0.0145, "y2": 0.9928}, "cname": "person", "score": 0.1725, "cid": 0}, {"bounding_box": {"y1": 0.1653, "x2": 0.4335, "x1": 0.1134, "y2": 0.9562}, "cname": "person", "score": 0.1519, "cid": 0}], [{"bounding_box": {"y1": 0.0853, "x2": 0.8995, "x1": 0.2926, "y2": 1.0}, "cname": "person", "score": 0.9126, "cid": 0}, {"bounding_box": {"y1": 0.0057, "x2": 0.5111, "x1": 0.0, "y2": 0.9646}, "cname": "person", "score": 0.201, "cid": 0}, {"bounding_box": {"y1": 0.5621, "x2": 0.3528, "x1": 0.005, "y2": 0.948}, "cname": "chair", "score": 0.128, "cid": 61}], [{"bounding_box": {"y1": 0.0749, "x2": 0.7066, "x1": 0.2471, "y2": 0.9938}, "cname": "person", "score": 0.7426, "cid": 0}, {"bounding_box": {"y1": 0.0, "x2": 0.6264, "x1": 0.0, "y2": 1.0}, "cname": "person", "score": 0.2428, "cid": 0}, {"bounding_box": {"y1": 0.387, "x2": 0.6312, "x1": 0.4922, "y2": 0.7585}, "cname": "person", "score": 0.1725, "cid": 0}, {"bounding_box": {"y1": 0.0714, "x2": 0.5755, "x1": 0.4053, "y2": 0.3159}, "cname": "person", "score": 0.1037, "cid": 0}], [{"bounding_box": {"y1": 0.1753, "x2": 0.7343, "x1": 0.308, "y2": 0.9925}, "cname": "person", "score": 0.7311, "cid": 0}, {"bounding_box": {"y1": 0.0325, "x2": 0.6238, "x1": 0.0, "y2": 0.9961}, "cname": "person", "score": 0.2428, "cid": 0}, {"bounding_box": {"y1": 0.0331, "x2": 0.2745, "x1": 0.0066, "y2": 0.9629}, "cname": "person", "score": 0.1408, "cid": 0}, {"bounding_box": {"y1": 0.2375, "x2": 0.9328, "x1": 0.0763, "y2": 0.9625}, "cname": "person", "score": 0.1067, "cid": 0}], [{"bounding_box": {"y1": 0.0596, "x2": 0.9966, "x1": 0.5626, "y2": 1.0}, "cname": "person", "score": 0.6071, "cid": 0}, {"bounding_box": {"y1": 0.1974, "x2": 0.6132, "x1": 0.3577, "y2": 0.8702}, "cname": "person", "score": 0.5985, "cid": 0}, {"bounding_box": {"y1": 0.0786, "x2": 0.3606, "x1": 0.0667, "y2": 1.0}, "cname": "person", "score": 0.5148, "cid": 0}, {"bounding_box": {"y1": 0.4933, "x2": 0.6008, "x1": 0.3471, "y2": 0.9817}, "cname": "person", "score": 0.3412, "cid": 0}, {"bounding_box": {"y1": 0.0035, "x2": 0.5407, "x1": 0.2907, "y2": 0.1783}, "cname": "chair", "score": 0.107, "cid": 61}], [{"bounding_box": {"y1": 0.169, "x2": 0.3696, "x1": 0.0178, "y2": 0.9926}, "cname": "person", "score": 0.6308, "cid": 0}, {"bounding_box": {"y1": 0.6115, "x2": 0.9918, "x1": 0.5757, "y2": 0.9951}, "cname": "sink", "score": 0.2456, "cid": 80}, {"bounding_box": {"y1": 0.8705, "x2": 0.8854, "x1": 0.6172, "y2": 1.0}, "cname": "person", "score": 0.1922, "cid": 0}, {"bounding_box": {"y1": 0.5424, "x2": 1.0, "x1": 0.3185, "y2": 0.9682}, "cname": "sink", "score": 0.1426, "cid": 80}, {"bounding_box": {"y1": 0.5165, "x2": 0.9792, "x1": 0.4803, "y2": 0.7708}, "cname": "sink", "score": 0.1252, "cid": 80}], [{"bounding_box": {"y1": 0.1615, "x2": 0.3894, "x1": 0.0486, "y2": 0.9957}, "cname": "person", "score": 0.5851, "cid": 0}, {"bounding_box": {"y1": 0.566, "x2": 0.8026, "x1": 0.5491, "y2": 0.9791}, "cname": "chair", "score": 0.3518, "cid": 61}, {"bounding_box": {"y1": 0.3254, "x2": 1.0, "x1": 0.7694, "y2": 0.9932}, "cname": "person", "score": 0.1167, "cid": 0}, {"bounding_box": {"y1": 0.7696, "x2": 0.9913, "x1": 0.8491, "y2": 0.9993}, "cname": "cup", "score": 0.1075, "cid": 46}, {"bounding_box": {"y1": 0.6212, "x2": 1.0, "x1": 0.6672, "y2": 0.9679}, "cname": "chair", "score": 0.1055, "cid": 61}], [{"bounding_box": {"y1": 0.1752, "x2": 0.9892, "x1": 0.625, "y2": 0.9885}, "cname": "person", "score": 0.4325, "cid": 0}, {"bounding_box": {"y1": 0.0, "x2": 0.2897, "x1": 0.0067, "y2": 0.9903}, "cname": "person", "score": 0.3948, "cid": 0}, {"bounding_box": {"y1": 0.4564, "x2": 0.6313, "x1": 0.3948, "y2": 0.9611}, "cname": "chair", "score": 0.3017, "cid": 61}, {"bounding_box": {"y1": 0.3251, "x2": 0.5265, "x1": 0.1836, "y2": 0.6743}, "cname": "chair", "score": 0.2252, "cid": 61}, {"bounding_box": {"y1": 0.0238, "x2": 0.2622, "x1": 0.0677, "y2": 0.7244}, "cname": "person", "score": 0.1911, "cid": 0}, {"bounding_box": {"y1": 0.3703, "x2": 0.597, "x1": 0.1623, "y2": 0.9012}, "cname": "chair", "score": 0.178, "cid": 61}, {"bounding_box": {"y1": 0.0415, "x2": 0.3065, "x1": 0.0151, "y2": 0.4723}, "cname": "person", "score": 0.1344, "cid": 0}, {"bounding_box": {"y1": 0.5224, "x2": 0.8317, "x1": 0.3978, "y2": 0.9701}, "cname": "chair", "score": 0.1279, "cid": 61}, {"bounding_box": {"y1": 0.1804, "x2": 0.8387, "x1": 0.6827, "y2": 0.468}, "cname": "potted plant", "score": 0.1143, "cid": 63}, {"bounding_box": {"y1": 0.0, "x2": 0.2629, "x1": 0.1075, "y2": 0.4336}, "cname": "backpack", "score": 0.1114, "cid": 26}], [{"bounding_box": {"y1": 0.0574, "x2": 0.6698, "x1": 0.0977, "y2": 0.997}, "cname": "person", "score": 0.7556, "cid": 0}, {"bounding_box": {"y1": 0.4736, "x2": 1.0, "x1": 0.5519, "y2": 0.9962}, "cname": "person", "score": 0.5276, "cid": 0}, {"bounding_box": {"y1": 0.4829, "x2": 0.999, "x1": 0.8055, "y2": 0.9867}, "cname": "person", "score": 0.1078, "cid": 0}], [{"bounding_box": {"y1": 0.2209, "x2": 0.5197, "x1": 0.1465, "y2": 0.9983}, "cname": "person", "score": 0.7184, "cid": 0}, {"bounding_box": {"y1": 0.0264, "x2": 0.9897, "x1": 0.6595, "y2": 1.0}, "cname": "person", "score": 0.5791, "cid": 0}, {"bounding_box": {"y1": 0.0255, "x2": 0.2436, "x1": 0.0, "y2": 0.9896}, "cname": "person", "score": 0.3621, "cid": 0}, {"bounding_box": {"y1": 0.0404, "x2": 0.1399, "x1": 0.009, "y2": 0.4747}, "cname": "person", "score": 0.1503, "cid": 0}], [{"bounding_box": {"y1": 0.1081, "x2": 0.9848, "x1": 0.5412, "y2": 0.9827}, "cname": "person", "score": 0.6738, "cid": 0}, {"bounding_box": {"y1": 0.0556, "x2": 0.5842, "x1": 0.0553, "y2": 0.9901}, "cname": "person", "score": 0.6568, "cid": 0}, {"bounding_box": {"y1": 0.4614, "x2": 0.2721, "x1": 0.0006, "y2": 0.9814}, "cname": "person", "score": 0.1541, "cid": 0}, {"bounding_box": {"y1": 0.2388, "x2": 0.1497, "x1": 0.0025, "y2": 0.9806}, "cname": "person", "score": 0.147, "cid": 0}, {"bounding_box": {"y1": 0.46, "x2": 0.4979, "x1": 0.1716, "y2": 0.865}, "cname": "backpack", "score": 0.1065, "cid": 26}], [{"bounding_box": {"y1": 0.0415, "x2": 0.6688, "x1": 0.0999, "y2": 0.9909}, "cname": "person", "score": 0.6177, "cid": 0}, {"bounding_box": {"y1": 0.0272, "x2": 0.9913, "x1": 0.5659, "y2": 1.0}, "cname": "person", "score": 0.4646, "cid": 0}], [{"bounding_box": {"y1": 0.0927, "x2": 0.6168, "x1": 0.0808, "y2": 0.9869}, "cname": "person", "score": 0.4913, "cid": 0}, {"bounding_box": {"y1": 0.0356, "x2": 0.993, "x1": 0.5673, "y2": 1.0}, "cname": "person", "score": 0.4103, "cid": 0}, {"bounding_box": {"y1": 0.3945, "x2": 0.1308, "x1": 0.0204, "y2": 0.5676}, "cname": "person", "score": 0.3583, "cid": 0}, {"bounding_box": {"y1": 0.579, "x2": 0.588, "x1": 0.1657, "y2": 0.9685}, "cname": "handbag", "score": 0.1537, "cid": 30}, {"bounding_box": {"y1": 0.6892, "x2": 0.8876, "x1": 0.4882, "y2": 0.9741}, "cname": "chair", "score": 0.1127, "cid": 61}, {"bounding_box": {"y1": 0.0878, "x2": 0.5193, "x1": 0.3392, "y2": 0.4169}, "cname": "person", "score": 0.1034, "cid": 0}], [{"bounding_box": {"y1": 0.0858, "x2": 0.9357, "x1": 0.2058, "y2": 0.9961}, "cname": "person", "score": 0.5282, "cid": 0}, {"bounding_box": {"y1": 0.0533, "x2": 0.6245, "x1": 0.0773, "y2": 0.9926}, "cname": "person", "score": 0.4814, "cid": 0}, {"bounding_box": {"y1": 0.0333, "x2": 0.9893, "x1": 0.704, "y2": 0.6022}, "cname": "vase", "score": 0.4625, "cid": 85}, {"bounding_box": {"y1": 0.0368, "x2": 0.9909, "x1": 0.6999, "y2": 0.6417}, "cname": "potted plant", "score": 0.3587, "cid": 63}, {"bounding_box": {"y1": 0.4028, "x2": 0.1124, "x1": 0.0107, "y2": 0.5667}, "cname": "person", "score": 0.3102, "cid": 0}, {"bounding_box": {"y1": 0.0337, "x2": 0.9743, "x1": 0.5092, "y2": 0.9202}, "cname": "person", "score": 0.1719, "cid": 0}, {"bounding_box": {"y1": 0.6226, "x2": 0.5415, "x1": 0.3679, "y2": 0.995}, "cname": "tie", "score": 0.1543, "cid": 31}, {"bounding_box": {"y1": 0.6265, "x2": 0.4735, "x1": 0.3236, "y2": 0.9875}, "cname": "tie", "score": 0.1388, "cid": 31}, {"bounding_box": {"y1": 0.5439, "x2": 0.4747, "x1": 0.3513, "y2": 0.8853}, "cname": "tie", "score": 0.1083, "cid": 31}], [{"bounding_box": {"y1": 0.091, "x2": 0.6431, "x1": 0.0596, "y2": 0.999}, "cname": "person", "score": 0.6351, "cid": 0}, {"bounding_box": {"y1": 0.0436, "x2": 0.9889, "x1": 0.6887, "y2": 0.6283}, "cname": "vase", "score": 0.3373, "cid": 85}, {"bounding_box": {"y1": 0.4074, "x2": 0.1204, "x1": 0.0077, "y2": 0.5591}, "cname": "person", "score": 0.3097, "cid": 0}, {"bounding_box": {"y1": 0.1451, "x2": 1.0, "x1": 0.3689, "y2": 0.9645}, "cname": "person", "score": 0.3074, "cid": 0}, {"bounding_box": {"y1": 0.029, "x2": 0.9918, "x1": 0.6935, "y2": 0.6557}, "cname": "potted plant", "score": 0.2166, "cid": 63}, {"bounding_box": {"y1": 0.5685, "x2": 1.0, "x1": 0.3852, "y2": 0.9965}, "cname": "person", "score": 0.1156, "cid": 0}, {"bounding_box": {"y1": 0.0266, "x2": 0.9845, "x1": 0.5481, "y2": 0.8878}, "cname": "potted plant", "score": 0.1102, "cid": 63}], [{"bounding_box": {"y1": 0.0979, "x2": 0.9923, "x1": 0.3997, "y2": 0.9858}, "cname": "person", "score": 0.6722, "cid": 0}, {"bounding_box": {"y1": 0.0651, "x2": 0.5304, "x1": 0.0762, "y2": 1.0}, "cname": "person", "score": 0.6338, "cid": 0}, {"bounding_box": {"y1": 0.4082, "x2": 0.123, "x1": 0.0075, "y2": 0.5674}, "cname": "person", "score": 0.3317, "cid": 0}, {"bounding_box": {"y1": 0.0554, "x2": 0.4502, "x1": 0.267, "y2": 0.483}, "cname": "person", "score": 0.1184, "cid": 0}], [{"bounding_box": {"y1": 0.0785, "x2": 0.5234, "x1": 0.142, "y2": 1.0}, "cname": "person", "score": 0.8232, "cid": 0}, {"bounding_box": {"y1": 0.0899, "x2": 0.8734, "x1": 0.4905, "y2": 0.995}, "cname": "person", "score": 0.5538, "cid": 0}, {"bounding_box": {"y1": 0.0043, "x2": 0.3174, "x1": 0.0106, "y2": 1.0}, "cname": "person", "score": 0.4491, "cid": 0}, {"bounding_box": {"y1": 0.0491, "x2": 0.1374, "x1": 0.0051, "y2": 0.4432}, "cname": "person", "score": 0.2132, "cid": 0}, {"bounding_box": {"y1": 0.3248, "x2": 0.6052, "x1": 0.4847, "y2": 0.6496}, "cname": "chair", "score": 0.1019, "cid": 61}], [{"bounding_box": {"y1": 0.0695, "x2": 0.5321, "x1": 0.1552, "y2": 1.0}, "cname": "person", "score": 0.8422, "cid": 0}, {"bounding_box": {"y1": 0.0971, "x2": 0.8754, "x1": 0.47, "y2": 0.9953}, "cname": "person", "score": 0.5529, "cid": 0}, {"bounding_box": {"y1": 0.0031, "x2": 0.3249, "x1": 0.0071, "y2": 0.9992}, "cname": "person", "score": 0.4322, "cid": 0}, {"bounding_box": {"y1": 0.0503, "x2": 0.7546, "x1": 0.2662, "y2": 1.0}, "cname": "person", "score": 0.3347, "cid": 0}], [{"bounding_box": {"y1": 0.0887, "x2": 0.8741, "x1": 0.0912, "y2": 0.994}, "cname": "person", "score": 0.7344, "cid": 0}, {"bounding_box": {"y1": 0.0583, "x2": 0.9909, "x1": 0.5171, "y2": 0.9703}, "cname": "person", "score": 0.1798, "cid": 0}, {"bounding_box": {"y1": 0.0336, "x2": 1.0, "x1": 0.7177, "y2": 0.652}, "cname": "person", "score": 0.1222, "cid": 0}], [{"bounding_box": {"y1": 0.0874, "x2": 0.7929, "x1": 0.0777, "y2": 0.996}, "cname": "person", "score": 0.693, "cid": 0}, {"bounding_box": {"y1": 0.1126, "x2": 1.0, "x1": 0.3918, "y2": 0.9867}, "cname": "person", "score": 0.2425, "cid": 0}, {"bounding_box": {"y1": 0.0562, "x2": 0.9984, "x1": 0.7204, "y2": 0.8931}, "cname": "person", "score": 0.1549, "cid": 0}, {"bounding_box": {"y1": 0.018, "x2": 0.9946, "x1": 0.7653, "y2": 0.5762}, "cname": "person", "score": 0.1279, "cid": 0}, {"bounding_box": {"y1": 0.3525, "x2": 0.9961, "x1": 0.7909, "y2": 0.6195}, "cname": "cup", "score": 0.1196, "cid": 46}], [{"bounding_box": {"y1": 0.0292, "x2": 0.512, "x1": 0.0356, "y2": 0.994}, "cname": "person", "score": 0.6509, "cid": 0}, {"bounding_box": {"y1": 0.1292, "x2": 0.9982, "x1": 0.7307, "y2": 0.9529}, "cname": "person", "score": 0.4703, "cid": 0}, {"bounding_box": {"y1": 0.0706, "x2": 0.9861, "x1": 0.5172, "y2": 0.9832}, "cname": "person", "score": 0.1647, "cid": 0}], [{"bounding_box": {"y1": 0.0824, "x2": 0.9929, "x1": 0.5874, "y2": 0.9986}, "cname": "person", "score": 0.6419, "cid": 0}, {"bounding_box": {"y1": 0.0165, "x2": 0.5666, "x1": 0.0019, "y2": 0.9986}, "cname": "person", "score": 0.4843, "cid": 0}, {"bounding_box": {"y1": 0.3422, "x2": 0.5423, "x1": 0.2283, "y2": 0.9925}, "cname": "person", "score": 0.2261, "cid": 0}, {"bounding_box": {"y1": 0.2708, "x2": 0.5151, "x1": 0.2283, "y2": 0.7104}, "cname": "person", "score": 0.1047, "cid": 0}], [{"bounding_box": {"y1": 0.1012, "x2": 0.7371, "x1": 0.322, "y2": 0.509}, "cname": "tv", "score": 0.9721, "cid": 71}, {"bounding_box": {"y1": 0.3724, "x2": 0.262, "x1": 0.0602, "y2": 0.9827}, "cname": "potted plant", "score": 0.5414, "cid": 63}, {"bounding_box": {"y1": 0.592, "x2": 0.2628, "x1": 0.1059, "y2": 0.9884}, "cname": "potted plant", "score": 0.4244, "cid": 63}, {"bounding_box": {"y1": 0.1789, "x2": 0.5669, "x1": 0.4338, "y2": 0.4948}, "cname": "person", "score": 0.3875, "cid": 0}, {"bounding_box": {"y1": 0.392, "x2": 0.239, "x1": 0.1006, "y2": 0.7689}, "cname": "potted plant", "score": 0.1848, "cid": 63}, {"bounding_box": {"y1": 0.1311, "x2": 0.7958, "x1": 0.2326, "y2": 0.7168}, "cname": "tv", "score": 0.1399, "cid": 71}], [{"bounding_box": {"y1": 0.2154, "x2": 0.8575, "x1": 0.0542, "y2": 0.9456}, "cname": "person", "score": 0.6074, "cid": 0}, {"bounding_box": {"y1": 0.3299, "x2": 0.7006, "x1": 0.3977, "y2": 0.6334}, "cname": "chair", "score": 0.2502, "cid": 61}, {"bounding_box": {"y1": 0.5155, "x2": 0.9947, "x1": 0.0449, "y2": 0.9856}, "cname": "couch", "score": 0.1985, "cid": 62}, {"bounding_box": {"y1": 0.3365, "x2": 0.7119, "x1": 0.3468, "y2": 0.94}, "cname": "chair", "score": 0.1764, "cid": 61}, {"bounding_box": {"y1": 0.1122, "x2": 0.9225, "x1": 0.7213, "y2": 0.5144}, "cname": "chair", "score": 0.151, "cid": 61}, {"bounding_box": {"y1": 0.3051, "x2": 0.7068, "x1": 0.0, "y2": 0.9691}, "cname": "couch", "score": 0.134, "cid": 62}, {"bounding_box": {"y1": 0.3831, "x2": 0.2493, "x1": 0.0837, "y2": 0.709}, "cname": "person", "score": 0.1276, "cid": 0}, {"bounding_box": {"y1": 0.4302, "x2": 0.9837, "x1": 0.5345, "y2": 0.9709}, "cname": "chair", "score": 0.122, "cid": 61}, {"bounding_box": {"y1": 0.4041, "x2": 0.9886, "x1": 0.4983, "y2": 0.971}, "cname": "person", "score": 0.1139, "cid": 0}, {"bounding_box": {"y1": 0.0258, "x2": 0.9846, "x1": 0.4304, "y2": 0.9073}, "cname": "person", "score": 0.1024, "cid": 0}], [{"bounding_box": {"y1": 0.0116, "x2": 0.2518, "x1": 0.0069, "y2": 0.5197}, "cname": "potted plant", "score": 0.6284, "cid": 63}, {"bounding_box": {"y1": 0.1347, "x2": 0.9874, "x1": 0.1085, "y2": 1.0}, "cname": "person", "score": 0.5882, "cid": 0}, {"bounding_box": {"y1": 0.2285, "x2": 0.8277, "x1": 0.473, "y2": 0.6999}, "cname": "chair", "score": 0.4143, "cid": 61}, {"bounding_box": {"y1": 0.1936, "x2": 0.8065, "x1": 0.2255, "y2": 0.72}, "cname": "chair", "score": 0.1717, "cid": 61}, {"bounding_box": {"y1": 0.3134, "x2": 0.8703, "x1": 0.492, "y2": 0.9577}, "cname": "chair", "score": 0.1476, "cid": 61}, {"bounding_box": {"y1": 0.4354, "x2": 0.7895, "x1": 0.3107, "y2": 0.8907}, "cname": "chair", "score": 0.1342, "cid": 61}, {"bounding_box": {"y1": 0.0185, "x2": 0.4283, "x1": 0.0126, "y2": 0.4182}, "cname": "potted plant", "score": 0.13, "cid": 63}], [{"bounding_box": {"y1": 0.1479, "x2": 0.9507, "x1": 0.1453, "y2": 0.946}, "cname": "person", "score": 0.5757, "cid": 0}, {"bounding_box": {"y1": 0.0115, "x2": 0.2319, "x1": 0.0039, "y2": 0.4831}, "cname": "potted plant", "score": 0.2831, "cid": 63}, {"bounding_box": {"y1": 0.0541, "x2": 0.8132, "x1": 0.4269, "y2": 0.612}, "cname": "chair", "score": 0.2288, "cid": 61}, {"bounding_box": {"y1": 0.4231, "x2": 0.715, "x1": 0.003, "y2": 0.9841}, "cname": "couch", "score": 0.2258, "cid": 62}, {"bounding_box": {"y1": 0.0643, "x2": 0.9901, "x1": 0.7705, "y2": 0.5971}, "cname": "chair", "score": 0.2169, "cid": 61}, {"bounding_box": {"y1": 0.0131, "x2": 0.375, "x1": 0.0, "y2": 0.3369}, "cname": "potted plant", "score": 0.1371, "cid": 63}, {"bounding_box": {"y1": 0.5635, "x2": 1.0, "x1": 0.6963, "y2": 0.9771}, "cname": "chair", "score": 0.1344, "cid": 61}, {"bounding_box": {"y1": 0.5059, "x2": 0.9905, "x1": 0.3832, "y2": 0.9773}, "cname": "chair", "score": 0.1279, "cid": 61}], [{"bounding_box": {"y1": 0.1584, "x2": 0.4439, "x1": 0.2084, "y2": 0.7216}, "cname": "person", "score": 0.9571, "cid": 0}, {"bounding_box": {"y1": 0.1973, "x2": 0.6595, "x1": 0.4334, "y2": 0.6953}, "cname": "person", "score": 0.9311, "cid": 0}, {"bounding_box": {"y1": 0.1289, "x2": 0.8908, "x1": 0.1557, "y2": 0.8085}, "cname": "tv", "score": 0.8781, "cid": 71}], [{"bounding_box": {"y1": 0.1513, "x2": 0.452, "x1": 0.2126, "y2": 0.7071}, "cname": "person", "score": 0.9412, "cid": 0}, {"bounding_box": {"y1": 0.114, "x2": 0.8813, "x1": 0.142, "y2": 0.7889}, "cname": "tv", "score": 0.9289, "cid": 71}, {"bounding_box": {"y1": 0.1939, "x2": 0.6419, "x1": 0.4173, "y2": 0.6912}, "cname": "person", "score": 0.8899, "cid": 0}], [{"bounding_box": {"y1": 0.1964, "x2": 0.4566, "x1": 0.2449, "y2": 0.7616}, "cname": "person", "score": 0.9614, "cid": 0}, {"bounding_box": {"y1": 0.1611, "x2": 0.9105, "x1": 0.1365, "y2": 0.8958}, "cname": "tv", "score": 0.938, "cid": 71}, {"bounding_box": {"y1": 0.2174, "x2": 0.6605, "x1": 0.4391, "y2": 0.7375}, "cname": "person", "score": 0.9285, "cid": 0}, {"bounding_box": {"y1": 0.2097, "x2": 0.7637, "x1": 0.2848, "y2": 0.778}, "cname": "tv", "score": 0.1833, "cid": 71}], [{"bounding_box": {"y1": 0.164, "x2": 0.4619, "x1": 0.2497, "y2": 0.736}, "cname": "person", "score": 0.9688, "cid": 0}, {"bounding_box": {"y1": 0.1982, "x2": 0.667, "x1": 0.4429, "y2": 0.7183}, "cname": "person", "score": 0.9556, "cid": 0}, {"bounding_box": {"y1": 0.1431, "x2": 0.8959, "x1": 0.1428, "y2": 0.8884}, "cname": "tv", "score": 0.7791, "cid": 71}, {"bounding_box": {"y1": 0.2938, "x2": 0.3172, "x1": 0.1918, "y2": 0.6853}, "cname": "refrigerator", "score": 0.1051, "cid": 81}], [{"bounding_box": {"y1": 0.355, "x2": 0.8024, "x1": 0.2466, "y2": 0.8892}, "cname": "keyboard", "score": 0.8888, "cid": 75}, {"bounding_box": {"y1": 0.358, "x2": 0.7608, "x1": 0.2641, "y2": 0.5811}, "cname": "keyboard", "score": 0.1138, "cid": 75}], [], [{"bounding_box": {"y1": 0.1937, "x2": 0.5645, "x1": 0.3128, "y2": 0.9769}, "cname": "person", "score": 0.6537, "cid": 0}, {"bounding_box": {"y1": 0.686, "x2": 0.5408, "x1": 0.3754, "y2": 0.9775}, "cname": "bottle", "score": 0.2509, "cid": 43}, {"bounding_box": {"y1": 0.2284, "x2": 0.5672, "x1": 0.3643, "y2": 0.5459}, "cname": "person", "score": 0.1807, "cid": 0}, {"bounding_box": {"y1": 0.6711, "x2": 0.3487, "x1": 0.2177, "y2": 0.8839}, "cname": "bottle", "score": 0.1416, "cid": 43}, {"bounding_box": {"y1": 0.3474, "x2": 0.6495, "x1": 0.5429, "y2": 0.6968}, "cname": "chair", "score": 0.1379, "cid": 61}, {"bounding_box": {"y1": 0.5923, "x2": 0.953, "x1": 0.0498, "y2": 1.0}, "cname": "dining table", "score": 0.1053, "cid": 66}, {"bounding_box": {"y1": 0.8353, "x2": 0.3625, "x1": 0.0445, "y2": 0.9897}, "cname": "dining table", "score": 0.1039, "cid": 66}, {"bounding_box": {"y1": 0.2292, "x2": 0.7118, "x1": 0.242, "y2": 0.8987}, "cname": "person", "score": 0.1035, "cid": 0}, {"bounding_box": {"y1": 0.7206, "x2": 0.9964, "x1": 0.6392, "y2": 0.9931}, "cname": "dining table", "score": 0.1016, "cid": 66}, {"bounding_box": {"y1": 0.5793, "x2": 0.8678, "x1": 0.6697, "y2": 0.7443}, "cname": "chair", "score": 0.1002, "cid": 61}], [{"bounding_box": {"y1": 0.193, "x2": 0.5865, "x1": 0.3077, "y2": 1.0}, "cname": "person", "score": 0.594, "cid": 0}, {"bounding_box": {"y1": 0.697, "x2": 0.7006, "x1": 0.5336, "y2": 0.9891}, "cname": "vase", "score": 0.3806, "cid": 85}, {"bounding_box": {"y1": 0.6834, "x2": 0.9993, "x1": 0.6882, "y2": 0.9742}, "cname": "dining table", "score": 0.2135, "cid": 66}, {"bounding_box": {"y1": 0.5676, "x2": 0.7536, "x1": 0.5227, "y2": 0.9659}, "cname": "chair", "score": 0.1845, "cid": 61}, {"bounding_box": {"y1": 0.3792, "x2": 0.7481, "x1": 0.5289, "y2": 0.8637}, "cname": "chair", "score": 0.1816, "cid": 61}, {"bounding_box": {"y1": 0.4236, "x2": 0.6745, "x1": 0.5366, "y2": 0.7163}, "cname": "chair", "score": 0.1658, "cid": 61}, {"bounding_box": {"y1": 0.2021, "x2": 0.5484, "x1": 0.3694, "y2": 0.518}, "cname": "person", "score": 0.1547, "cid": 0}, {"bounding_box": {"y1": 0.6477, "x2": 0.5385, "x1": 0.36, "y2": 0.9873}, "cname": "bottle", "score": 0.1498, "cid": 43}, {"bounding_box": {"y1": 0.7315, "x2": 0.9963, "x1": 0.7694, "y2": 0.8963}, "cname": "dining table", "score": 0.1469, "cid": 66}, {"bounding_box": {"y1": 0.4646, "x2": 0.45, "x1": 0.3086, "y2": 0.7105}, "cname": "handbag", "score": 0.1363, "cid": 30}, {"bounding_box": {"y1": 0.4833, "x2": 0.311, "x1": 0.1754, "y2": 0.8639}, "cname": "bottle", "score": 0.1336, "cid": 43}, {"bounding_box": {"y1": 0.2052, "x2": 0.4801, "x1": 0.3355, "y2": 0.4845}, "cname": "person", "score": 0.111, "cid": 0}, {"bounding_box": {"y1": 0.431, "x2": 0.1936, "x1": 0.0777, "y2": 0.7078}, "cname": "bottle", "score": 0.1097, "cid": 43}, {"bounding_box": {"y1": 0.8312, "x2": 0.5605, "x1": 0.3302, "y2": 0.9936}, "cname": "bottle", "score": 0.1092, "cid": 43}, {"bounding_box": {"y1": 0.0729, "x2": 0.6683, "x1": 0.3071, "y2": 0.7569}, "cname": "person", "score": 0.1091, "cid": 0}, {"bounding_box": {"y1": 0.6392, "x2": 0.9814, "x1": 0.5372, "y2": 0.9157}, "cname": "dining table", "score": 0.105, "cid": 66}], [{"bounding_box": {"y1": 0.0772, "x2": 1.0, "x1": 0.0345, "y2": 1.0}, "cname": "person", "score": 0.1022, "cid": 0}], [{"bounding_box": {"y1": 0.0772, "x2": 1.0, "x1": 0.0345, "y2": 1.0}, "cname": "person", "score": 0.1022, "cid": 0}], [{"bounding_box": {"y1": 0.0772, "x2": 1.0, "x1": 0.0345, "y2": 1.0}, "cname": "person", "score": 0.1022, "cid": 0}]]