[[], [], [], [], [], [], [], [{"affectnet": 0, "activated": 0.068, "pleasant": -0.096, "bounding_box": {"y1": 0.278, "x2": 0.278, "x1": 0.141, "y2": 0.528}, "score": 1.0, "expression_score": 0.982, "expression": "neutral"}, {"affectnet": 0, "activated": -0.02, "pleasant": -0.068, "bounding_box": {"y1": 0.211, "x2": 0.856, "x1": 0.694, "y2": 0.506}, "score": 1.0, "expression_score": 0.996, "expression": "neutral"}], [{"affectnet": 0, "activated": -0.055, "pleasant": 0.198, "bounding_box": {"y1": 0.244, "x2": 0.3, "x1": 0.134, "y2": 0.533}, "score": 1.0, "expression_score": 0.773, "expression": "neutral"}, {"affectnet": 0, "activated": -0.024, "pleasant": 0.03, "bounding_box": {"y1": 0.211, "x2": 0.841, "x1": 0.675, "y2": 0.506}, "score": 1.0, "expression_score": 0.967, "expression": "neutral"}], [], [{"affectnet": 0, "activated": -0.044, "pleasant": -0.042, "bounding_box": {"y1": 0.167, "x2": 0.278, "x1": 0.041, "y2": 0.589}, "score": 1.0, "expression_score": 0.998, "expression": "neutral"}], [], [], [], [], []]