[[], [], [{"affectnet": 0, "activated": -0.05, "pleasant": -0.107, "bounding_box": {"y1": 0.211, "x2": 0.356, "x1": 0.119, "y2": 0.633}, "score": 1.0, "expression_score": 0.973, "expression": "neutral"}], [], [], [], [], [], [], [], [], [], [], [], [], [], [], [{"affectnet": 0, "activated": 0.05, "pleasant": -0.195, "bounding_box": {"y1": 0.211, "x2": 0.406, "x1": 0.291, "y2": 0.417}, "score": 1.0, "expression_score": 0.969, "expression": "neutral"}], [{"affectnet": 0, "activated": -0.014, "pleasant": 0.303, "bounding_box": {"y1": 0.311, "x2": 0.613, "x1": 0.331, "y2": 0.817}, "score": 1.0, "expression_score": 0.487, "expression": "neutral"}], [], [], [], [], [], [], [], [], [], [{"affectnet": 0, "activated": 0.595, "pleasant": 0.076, "bounding_box": {"y1": 0.133, "x2": 0.616, "x1": 0.209, "y2": 0.856}, "score": 1.0, "expression_score": 0.591, "expression": "fear"}], [], [], [], [{"affectnet": 0, "activated": -0.027, "pleasant": 0.407, "bounding_box": {"y1": 0.372, "x2": 0.822, "x1": 0.656, "y2": 0.661}, "score": 1.0, "expression_score": 0.608, "expression": "happy"}], [], [], [], [], [], [], [], [], [], [], [], [], [], [{"affectnet": 0, "activated": 0.104, "pleasant": 0.555, "bounding_box": {"y1": 0.406, "x2": 0.553, "x1": 0.356, "y2": 0.756}, "score": 1.0, "expression_score": 0.999, "expression": "happy"}], [], [], [], [], [], [], [], [], [], [], [], [], [], []]